dbify/__init__.py
dbify/config_file.py
dbify/connections.py
dbify/dbify.py
dbify-0.0.1.dist-info/LICENSE
dbify-0.0.1.dist-info/METADATA
dbify-0.0.1.dist-info/WHEEL
dbify-0.0.1.dist-info/top_level.txt
dbify-0.0.1.dist-info/RECORD
