Metadata-Version: 2.1
Name: dbify
Version: 0.0.1
Summary: decorator for storing function results in a database
Home-page: UNKNOWN
Author: Klas Leino
Author-email: kleino@cs.cmu.edu
License: UNKNOWN
Platform: UNKNOWN
Classifier: Programming Language :: Python :: 3
Classifier: License :: OSI Approved :: MIT License
Classifier: Operating System :: OS Independent
Requires-Python: >=3.6
License-File: LICENSE
Requires-Dist: mysql-connector-python
Requires-Dist: decorator
Requires-Dist: sshtunnel
